openplugin_sdk/__init__.py
openplugin_sdk/base.py
openplugin_sdk-0.1.5.dist-info/METADATA
openplugin_sdk-0.1.5.dist-info/WHEEL
openplugin_sdk-0.1.5.dist-info/RECORD
