Metadata-Version: 2.1
Name: openplugin-sdk
Version: 0.1.5
Summary: 
Author: shrikant
Author-email: shrikant.pm14@gmail.com
Requires-Python: >=3.9,<4.0
Classifier: Programming Language :: Python :: 3
Classifier: Programming Language :: Python :: 3.9
Classifier: Programming Language :: Python :: 3.10
Classifier: Programming Language :: Python :: 3.11
Requires-Dist: httpx (>=0.27.0,<0.28.0)
Requires-Dist: pydantic (>=2.6.3,<3.0.0)
